comp1010/__init__.py
comp1010/__main__.py
comp1010-25.1.7.dist-info/LICENSE.md
comp1010-25.1.7.dist-info/METADATA
comp1010-25.1.7.dist-info/WHEEL
comp1010-25.1.7.dist-info/entry_points.txt
comp1010-25.1.7.dist-info/RECORD
