Metadata-Version: 2.3
Name: comp1010
Version: 25.1.7
Summary: The COMP1010 metapackage, used to specify dependencies required for UNSW's COMP1010 course.
License: # MIT License
Author: COMP1010 UNSW
Author-email: cs1010@cse.unsw.edu.au
Requires-Python: >=3.11
Classifier: License :: Other/Proprietary License
Classifier: Programming Language :: Python :: 3
Classifier: Programming Language :: Python :: 3.11
Classifier: Programming Language :: Python :: 3.12
Classifier: Programming Language :: Python :: 3.13
Requires-Dist: colorama (>=0.4.6,<0.5.0)
Requires-Dist: flask (>=3.1.0,<4.0.0)
Requires-Dist: ipykernel (>=6.29.5,<7.0.0)
Requires-Dist: jestspectation (>=1.4.3,<2.0.0)
Requires-Dist: mypy (>=1.15.0,<2.0.0)
Requires-Dist: numpy (>=2.2.2,<3.0.0)
Requires-Dist: pandas (>=2.2.3,<3.0.0)
Requires-Dist: pillow (>=11.1.0,<12.0.0)
Requires-Dist: pyhtml-enhanced (>=2.2.0,<3.0.0)
Requires-Dist: pytest (>=8.3.4,<9.0.0)
Requires-Dist: requests (>=2.32.3,<3.0.0)
Requires-Dist: subtask (>=1.1.2,<2.0.0)
Requires-Dist: types-colorama (>=0.4.15.20240311,<0.5.0.0)
Requires-Dist: types-requests (>=2.32.0.20241016,<3.0.0.0)
